api/__init__.py
api/api.py
drivers/__init__.py
drivers/chrome_driver.py
drivers/driver_factory.py
drivers/edge_driver.py
drivers/firefox_driver.py
drivers/webdriver_setup.py
utilities/__init__.py
utilities/logging_setup.py
utilities/browser_actions/__init__.py
utilities/browser_actions/browser_actions_setup.py
utilities/decorators/__init__.py
utilities/decorators/decorators_setup.py
utilities/element_waiters/__init__.py
utilities/element_waiters/element_waiters_setup.py
selenium_driver_setup-0.1.2.dist-info/LICENSE
selenium_driver_setup-0.1.2.dist-info/METADATA
selenium_driver_setup-0.1.2.dist-info/WHEEL
selenium_driver_setup-0.1.2.dist-info/top_level.txt
selenium_driver_setup-0.1.2.dist-info/RECORD
