Metadata-Version: 2.1
Name: selenium-driver-setup
Version: 0.1.2
Summary: A utility package for Selenium WebDriver setup and handling.
Home-page: https://github.com/The-Deep-Hub/selenium-setup
Author: Jorge Cardete
Author-email: publication@deephublearning.com
Classifier: Development Status :: 3 - Alpha
Classifier: Intended Audience :: Developers
Classifier: Topic :: Software Development :: Libraries
Classifier: License :: OSI Approved :: Apache Software License
Classifier: Programming Language :: Python :: 3
Classifier: Programming Language :: Python :: 3.6
Classifier: Programming Language :: Python :: 3.7
Classifier: Programming Language :: Python :: 3.8
Classifier: Programming Language :: Python :: 3.9
Requires-Python: >=3.6
License-File: LICENSE
Requires-Dist: selenium>=3.141.0
Requires-Dist: webdriver-manager>=3.2.0
